{
  "AG": { "nom": "Argovie",                       "url": "https://www.sva-ag.ch/pv",               "langue": "de" },
  "AI": { "nom": "Appenzell Rhodes-Intérieures",   "url": "https://www.ai.ch/",                     "langue": "de" },
  "AR": { "nom": "Appenzell Rhodes-Extérieures",   "url": "http://www.sovar.ch/",                   "langue": "de" },
  "BE": { "nom": "Berne",                          "url": "https://www.asv.dij.be.ch",              "langue": "de" },
  "BL": { "nom": "Bâle-Campagne",                  "url": "https://www.sva-bl.ch/",                 "langue": "de" },
  "BS": { "nom": "Bâle-Ville",                     "url": "https://www.asb.bs.ch/",                 "langue": "de" },
  "FR": { "nom": "Fribourg",                       "url": "https://www.ecasfr.ch/",                 "langue": "fr" },
  "GE": { "nom": "Genève",                         "url": "https://www.ge.ch",                      "langue": "fr" },
  "GL": { "nom": "Glaris",                         "url": "https://www.gl.ch/",                     "langue": "de" },
  "GR": { "nom": "Grisons",                        "url": "https://www.sva.gr.ch/",                 "langue": "de" },
  "JU": { "nom": "Jura",                           "url": "https://www.ecasjura.ch/",               "langue": "fr" },
  "LU": { "nom": "Lucerne",                        "url": "http://www.was-luzern.ch/ak",            "langue": "de" },
  "NE": { "nom": "Neuchâtel",                      "url": "https://www.ne.ch/",                     "langue": "fr" },
  "NW": { "nom": "Nidwald",                        "url": "http://www.aknw.ch/",                    "langue": "de" },
  "OW": { "nom": "Obwald",                         "url": "https://www.akow.ch/ipv",                "langue": "de" },
  "SG": { "nom": "Saint-Gall",                     "url": "https://www.svasg.ch/ipv",               "langue": "de" },
  "SH": { "nom": "Schaffhouse",                    "url": "https://www.svash.ch/",                  "langue": "de" },
  "SO": { "nom": "Soleure",                        "url": "http://www.akso.ch/",                    "langue": "de" },
  "SZ": { "nom": "Schwyz",                         "url": "http://www.aksz.ch/",                    "langue": "de" },
  "TG": { "nom": "Thurgovie",                      "url": "https://gesundheit.tg.ch/",              "langue": "de" },
  "TI": { "nom": "Tessin",                         "url": "https://www.ti.ch/",                     "langue": "it" },
  "UR": { "nom": "Uri",                            "url": "https://www.ur.ch/praemienverbilligung", "langue": "de" },
  "VD": { "nom": "Vaud",                           "url": "https://www.vd.ch",                      "langue": "fr" },
  "VS": { "nom": "Valais",                         "url": "https://www.avs.vs.ch/",                 "langue": "fr" },
  "ZG": { "nom": "Zoug",                           "url": "https://www.akzug.ch/ipv/",              "langue": "de" },
  "ZH": { "nom": "Zurich",                         "url": "https://svazurich.ch",                   "langue": "de" }
}
